statecli/__init__.py
statecli/client.py
statecli/error_recovery.py
statecli/file_tracker.py
statecli/git_integration.py
statecli/langchain_tools.py
statecli/types.py
statecli-0.5.0.dist-info/METADATA
statecli-0.5.0.dist-info/WHEEL
statecli-0.5.0.dist-info/RECORD
