Metadata-Version: 2.4
Name: statecli
Version: 0.5.0
Summary: State Replay & Self-Debugging for AI Agents - Track, replay, undo, and checkpoint state changes
Project-URL: Homepage, https://github.com/statecli/mcp-server
Project-URL: Documentation, https://github.com/statecli/mcp-server#readme
Project-URL: Repository, https://github.com/statecli/mcp-server
Project-URL: Issues, https://github.com/statecli/mcp-server/issues
Author-email: StateCLI <support@statecli.dev>
License-Expression: MIT
Keywords: agent-memory,ai-agent-tools,autogpt,autonomous-agents,checkpoint,crewai,langchain,mcp-server,model-context-protocol,rollback,self-debugging,state-management,state-replay,time-travel-debugging,undo
Classifier: Development Status :: 4 - Beta
Classifier: Intended Audience :: Developers
Classifier: License :: OSI Approved :: MIT License
Classifier: Operating System :: OS Independent
Classifier: Programming Language :: Python :: 3
Classifier: Programming Language :: Python :: 3.8
Classifier: Programming Language :: Python :: 3.9
Classifier: Programming Language :: Python :: 3.10
Classifier: Programming Language :: Python :: 3.11
Classifier: Programming Language :: Python :: 3.12
Classifier: Topic :: Software Development :: Debuggers
Classifier: Topic :: Software Development :: Libraries :: Python Modules
Requires-Python: >=3.8
